Metadata-Version: 1.0
Name: banner-comment
Version: 0.0.4
Summary: An ASCII banner comment generator for making subl nicer.
Home-page: https://github.com/jbn/banner_comment
Author: John Bjorn Nelson
Author-email: jbn@abreka.com
License: License :: OSI Approved :: MIT License
Platform: UNKNOWN
